rai_modules/__init__.py
rai_modules/math_utils.py
rai_modules/python_utils.py
Rai_modules-0.1.3.dist-info/LICENSE
Rai_modules-0.1.3.dist-info/METADATA
Rai_modules-0.1.3.dist-info/WHEEL
Rai_modules-0.1.3.dist-info/top_level.txt
Rai_modules-0.1.3.dist-info/RECORD
