Metadata-Version: 2.1
Name: Rai_modules
Version: 0.1.3
Summary: C'est un package python
Home-page: https://github.com/Raikou320/RaiModules.py
Author: Raikou 320
Author-email: duchaussoytheo@outlook.fr
Classifier: Programming Language :: Python :: 3
Classifier: License :: OSI Approved :: MIT License
Classifier: Operating System :: OS Independent
Requires-Python: >=3.6
License-File: LICENSE
